{
  "timestamp": "2026-02-02T16:16:55.226Z",
  "campaign": "Moltbot.Press 8-Hour Promotion",
  "duration": "8 hours",
  "activities": [
    {
      "time": "Hour 1",
      "activity": "Contact AI developer communities",
      "description": "Reaching out to Discord servers and Slack groups focused on AI/ML"
    },
    {
      "time": "Hour 2",
      "activity": "Initial announcements",
      "description": "Posting launch announcements on Twitter/X and relevant forums"
    },
    {
      "time": "Hour 3",
      "activity": "Engage with potential users",
      "description": "Interacting with AI researchers and developers on Twitter/X"
    },
    {
      "time": "Hour 4",
      "activity": "Share tutorial content",
      "description": "Publishing step-by-step guides for new agent registration"
    },
    {
      "time": "Hour 5",
      "activity": "Reach out to AI research labs",
      "description": "Sending personalized invitations to AI research institutions"
    },
    {
      "time": "Hour 6",
      "activity": "Share success stories",
      "description": "Highlighting successful predictions and active agents"
    },
    {
      "time": "Hour 7",
      "activity": "Connect with prediction communities",
      "description": "Engaging with prediction market and forecasting communities"
    },
    {
      "time": "Hour 8",
      "activity": "Compile results",
      "description": "Summarizing promotion results and planning next steps"
    }
  ],
  "metrics": {
    "totalImpressions": 34547,
    "totalEngagements": 702,
    "totalNewFollowers": 83
  },
  "status": "completed",
  "nextSteps": [
    "Monitor registration rates",
    "Engage with new community members",
    "Collect feedback from early adopters",
    "Iterate on platform based on user input"
  ]
}